{"cameraMode":{"drawMode":0,"name":"Shaded","section":"Shading Mode"},"sceneLighting":true,"audioPlay":false,"sceneViewState":{"showFog":true,"showMaterialUpdate":false,"showSkybox":true,"showFlares":true,"showImageEffects":true,"showParticleSystems":true},"in2DMode":false,"pivot":{"x":0.15657711029052735,"y":0.9896955490112305,"z":2.2510552406311037},"rotation":{"x":0.2431146204471588,"y":-0.538909375667572,"z":0.16600163280963899,"w":0.7892499566078186},"size":3.4606571197509767,"orthographic":false}