{"cameraMode":{"drawMode":0,"name":"Shaded","section":"Shading Mode"},"sceneLighting":true,"audioPlay":false,"sceneViewState":{"showFog":true,"showMaterialUpdate":false,"showSkybox":true,"showFlares":true,"showImageEffects":true,"showParticleSystems":true},"in2DMode":false,"pivot":{"x":0.20662760734558106,"y":0.42876386642456057,"z":0.6454982757568359},"rotation":{"x":0.17144005000591279,"y":-0.07587374746799469,"z":0.013243713416159153,"w":0.9821792840957642},"size":3.8995072841644289,"orthographic":false}